nagios_mcp/__init__.py
nagios_mcp/__main__.py
nagios_mcp/server.py
nagios_mcp/tools/__init__.py
nagios_mcp/tools/config_tools.py
nagios_mcp/tools/status_tools.py
nagios_mcp/tools/tools.py
nagios_mcp/tools/utils.py
nagios_mcp-0.1.4.dist-info/licenses/LICENSE
nagios_mcp-0.1.4.dist-info/METADATA
nagios_mcp-0.1.4.dist-info/WHEEL
nagios_mcp-0.1.4.dist-info/entry_points.txt
nagios_mcp-0.1.4.dist-info/top_level.txt
nagios_mcp-0.1.4.dist-info/RECORD
