Metadata-Version: 2.4
Name: nagios-mcp
Version: 0.1.4
Summary: MCP Server for Nagios Core
Author-email: Umang Kaushik <umang.kaushik@prospiretech.com>
License: Apache-2.0
Project-URL: Homepage, https://github.com/PROSPIRE-TECHNOLOGY-SERVICES/nagios-mcp
Project-URL: Repository, https://github.com/PROSPIRE-TECHNOLOGY-SERVICES/nagios-mcp
Requires-Python: >=3.12
License-File: LICENSE
Requires-Dist: flask>=3.1.1
Requires-Dist: mcp[cli]>=1.8.0
Requires-Dist: pyyaml>=6.0.2
Requires-Dist: requests>=2.32.3
Dynamic: license-file
